sfdLib/__init__.py
sfdLib/__main__.py
sfdLib/parser.py
sfdLib/utils.py
sfdLib-2.0.0.post0.dist-info/AUTHORS
sfdLib-2.0.0.post0.dist-info/LICENSE
sfdLib-2.0.0.post0.dist-info/LICENSE.orig
sfdLib-2.0.0.post0.dist-info/METADATA
sfdLib-2.0.0.post0.dist-info/WHEEL
sfdLib-2.0.0.post0.dist-info/entry_points.txt
sfdLib-2.0.0.post0.dist-info/top_level.txt
sfdLib-2.0.0.post0.dist-info/RECORD
